digicon_mod/__init__.py
digicon_mod/pid.py
digicon_mod/plc.py
digicon_mod/sim.py
digicon_mod/test/__init__.py
digicon_mod/test/pid_control.py
digicon_mod-0.1.4.dist-info/LICENSE
digicon_mod-0.1.4.dist-info/METADATA
digicon_mod-0.1.4.dist-info/WHEEL
digicon_mod-0.1.4.dist-info/RECORD
